pybeeryaml/__init__.py
pybeeryaml/fermentable.py
pybeeryaml/hop.py
pybeeryaml/mash.py
pybeeryaml/meta.py
pybeeryaml/misc.py
pybeeryaml/recipe.py
pybeeryaml/style.py
pybeeryaml/water.py
pybeeryaml/yeast.py
pybeeryaml-1.3.dist-info/LICENSE
pybeeryaml-1.3.dist-info/METADATA
pybeeryaml-1.3.dist-info/WHEEL
pybeeryaml-1.3.dist-info/top_level.txt
pybeeryaml-1.3.dist-info/RECORD
