Metadata-Version: 2.1
Name: pybeeryaml
Version: 1.3
Summary: PyBeerYAML A YAML format parser for beer storage
Home-page: https://pythonhosted.org/pybeeryaml/
Author: TROUVERIE Joachim
Author-email: jtrouverie@joakode.fr
License: UNKNOWN
Download-URL: https://github.com/j0ack/pybeeryaml
Platform: UNKNOWN
Classifier: Development Status :: 4 - Beta
Classifier: Environment :: Console
Classifier: License :: OSI Approved :: GNU General Public License v3 or later (GPLv3+)
Classifier: Natural Language :: English
Classifier: Programming Language :: Python :: 3.5
Classifier: Programming Language :: Python :: 3.6
Classifier: Programming Language :: Python :: 3.7
Classifier: Programming Language :: Python :: 3.8
Classifier: Topic :: Utilities
Requires-Dist: pyyaml
